src/__init__.py
src/cache.py
src/persistence.py
tests/__init__.py
tests/test_cache.py
tests/test_persistence.py
atikin_cache-1.0.0.dist-info/LICENSE
atikin_cache-1.0.0.dist-info/METADATA
atikin_cache-1.0.0.dist-info/WHEEL
atikin_cache-1.0.0.dist-info/top_level.txt
atikin_cache-1.0.0.dist-info/RECORD
