Metadata-Version: 2.1
Name: atikin-cache
Version: 1.0.0
Summary: High-performance in-memory caching library with TTL, LRU eviction, and persistence.
Home-page: https://github.com/atikinverse/atikin-cache
Author: Atikin Verse
Author-email: atikinverse@gmail.com
Keywords: cache caching memory ttl lru performance atikin cache
Classifier: Development Status :: 5 - Production/Stable
Classifier: Intended Audience :: Developers
Classifier: License :: OSI Approved :: MIT License
Classifier: Operating System :: OS Independent
Classifier: Programming Language :: Python :: 3
Classifier: Programming Language :: Python :: 3.7
Classifier: Programming Language :: Python :: 3.8
Classifier: Programming Language :: Python :: 3.9
Classifier: Programming Language :: Python :: 3.10
Classifier: Programming Language :: Python :: 3.11
Classifier: Topic :: Software Development :: Libraries
Classifier: Topic :: Utilities
Requires-Python: >=3.7
License-File: LICENSE
